blxo/__init__.py
blxo/geometry.py
blxo/math_physics.py
blxo/mc.py
blxo/vector_angle.py
blxo-0.1.13.dist-info/METADATA
blxo-0.1.13.dist-info/WHEEL
blxo-0.1.13.dist-info/entry_points.txt
blxo-0.1.13.dist-info/top_level.txt
blxo-0.1.13.dist-info/RECORD
