Metadata-Version: 2.1
Name: blxo
Version: 0.1.13
Summary: Bent Laue Monochromators X-ray Optics
Home-page: https://github.com/darwinqii/bent-laue-xray-optics
Author: Peng Qi
Author-email: peng.qi@usask.ca
License: UNKNOWN
Platform: UNKNOWN
Requires-Dist: matplotlib
Requires-Dist: numpy
Requires-Dist: pandas
Requires-Dist: pathlib
Requires-Dist: scipy (>=1.2.1)
